[
    {
        "recommended_id": 1143,
        "type": 1,
        "message": "",
        "reward_id": 101,
        "start_date": "2023-06-16 00:00:00",
        "end_date": "2023-06-16 23:59:59",
        "recommended_music_list": [
            {
                "recommended_no": 1,
                "music_id": 15004
            },
            {
                "recommended_no": 0,
                "music_id": 27032
            },
            {
                "recommended_no": 2,
                "music_id": 29051
            }
        ]
    },
    {
        "recommended_id": 5148,
        "type": 2,
        "message": "ボーカル曲をセレクト♪",
        "reward_id": 0,
        "start_date": "2023-06-12 00:00:00",
        "end_date": "2023-06-18 23:59:59",
        "recommended_music_list": [
            {
                "recommended_no": 0,
                "music_id": 11007
            },
            {
                "recommended_no": 1,
                "music_id": 25079
            }
        ]
    }
]