{
    "ranking": {
        "skill_0_999": [
            5001,
            1627,
            21,
            5039,
            5043,
            2730,
            2238,
            1530,
            1701,
            1648,
            2645,
            1235,
            1147,
            734,
            5013,
            2968,
            2966,
            2733,
            2421,
            2413,
            2399,
            2373,
            2298,
            2122,
            2091,
            1906,
            1846,
            1845,
            1804,
            1339,
            731,
            626,
            621,
            517,
            207,
            120,
            5092,
            5084,
            5078,
            5073,
            5042,
            5041,
            5034,
            5032,
            5025,
            5018,
            2820,
            2768,
            2710,
            2709
        ],
        "skill_1000_1499": [
            2645,
            2399,
            1952,
            2640,
            1846,
            2820,
            2709,
            2605,
            2730,
            2618,
            2421,
            2373,
            2085,
            1542,
            1235,
            1129,
            929,
            926,
            601,
            2710,
            2362,
            2177,
            1984,
            1906,
            1847,
            908,
            726,
            722,
            626,
            517,
            21,
            2708,
            2412,
            2238,
            2236,
            2091,
            1965,
            1964,
            1951,
            1940,
            1845,
            1620,
            1530,
            1403,
            1217,
            1111,
            1008,
            960,
            836,
            828
        ],
        "skill_1500_1999": [
            2238,
            2708,
            601,
            2710,
            2605,
            2709,
            2602,
            2319,
            1530,
            2645,
            2399,
            2382,
            2303,
            1984,
            1542,
            1129,
            2730,
            2566,
            2362,
            2239,
            517,
            21,
            2640,
            2618,
            2443,
            2177,
            2134,
            2096,
            2082,
            1956,
            1951,
            1846,
            1740,
            1721,
            1105,
            2470,
            2415,
            2412,
            2388,
            1965,
            1952,
            1940,
            1847,
            1845,
            1648,
            1403,
            960,
            738,
            207,
            133
        ],
        "skill_2000_2499": [
            1530,
            2238,
            2709,
            2708,
            2640,
            2618,
            2399,
            517,
            2730,
            2710,
            2421,
            2415,
            2388,
            2382,
            1940,
            1403,
            2820,
            2602,
            2522,
            2443,
            2373,
            2605,
            2239,
            2177,
            2091,
            1952,
            1740,
            1519,
            606,
            601,
            1846,
            1725,
            1542,
            836,
            828,
            2527,
            2428,
            2362,
            2127,
            1845,
            1204,
            1037,
            734,
            2645,
            2487,
            2474,
            2430,
            2404,
            2189,
            2122
        ],
        "skill_2500_2999": [
            2421,
            1963,
            2820,
            2581,
            2137,
            2709,
            2602,
            1530,
            2730,
            2708,
            2645,
            1627,
            960,
            2618,
            2605,
            517,
            2710,
            2640,
            2470,
            910,
            2522,
            2404,
            2189,
            1962,
            207,
            2540,
            2487,
            2476,
            2443,
            2082,
            1217,
            836,
            722,
            601,
            2560,
            2388,
            2382,
            2319,
            2238,
            2127,
            804,
            501,
            2600,
            1975,
            1940,
            1701,
            1542,
            1517,
            726,
            704
        ],
        "skill_3000_3499": [
            1530,
            2421,
            2709,
            2602,
            2708,
            2605,
            2137,
            2238,
            722,
            2640,
            1701,
            517,
            2820,
            2710,
            2645,
            1715,
            1627,
            2189,
            1846,
            1542,
            717,
            2581,
            2127,
            1129,
            2618,
            2566,
            2388,
            1725,
            1620,
            960,
            2476,
            2470,
            2443,
            1213,
            1008,
            307,
            2730,
            2399,
            910,
            804,
            501,
            2465,
            1217,
            805,
            514,
            403,
            2599,
            2500,
            1965,
            1517
        ],
        "skill_3500_3999": [
            1701,
            1530,
            2605,
            2602,
            2566,
            2710,
            2645,
            2137,
            2421,
            1715,
            2820,
            2500,
            2640,
            2600,
            1620,
            717,
            2708,
            1429,
            2709,
            1963,
            1517,
            2606,
            2470,
            1984,
            2189,
            1965,
            1217,
            722,
            2618,
            2465,
            403,
            2341,
            2303,
            1627,
            1129,
            910,
            805,
            2599,
            2581,
            2442,
            1213,
            2404,
            1846,
            1635,
            2388,
            2238,
            2134,
            1962,
            1105,
            917
        ],
        "skill_4000_4499": [
            2605,
            1530,
            1715,
            2710,
            2645,
            1701,
            2566,
            2602,
            2600,
            2421,
            1984,
            2581,
            2640,
            2560,
            2606,
            2442,
            403,
            2820,
            1963,
            1635,
            2599,
            2388,
            2189,
            1627,
            1517,
            1213,
            2500,
            2341,
            601,
            2709,
            2156,
            1965,
            804,
            722,
            2137,
            2082,
            717,
            2238,
            1620,
            305,
            2708,
            2404,
            2412,
            2298,
            1008,
            910,
            2618,
            2470,
            2465,
            2443
        ],
        "skill_4500_4999": [
            2605,
            2600,
            1530,
            2645,
            1627,
            1701,
            1213,
            1715,
            2421,
            2640,
            2606,
            1620,
            2500,
            403,
            2082,
            1517,
            2566,
            2560,
            2137,
            2599,
            2581,
            2341,
            1635,
            1984,
            2710,
            2189,
            2476,
            2388,
            601,
            307,
            2730,
            2442,
            2382,
            1217,
            801,
            2820,
            2602,
            305,
            2498,
            1728,
            1610,
            1433,
            706,
            2618,
            2134,
            1962,
            1603,
            836,
            2708,
            2319
        ],
        "skill_5000_5499": [
            2605,
            2645,
            2560,
            1715,
            2600,
            2388,
            1627,
            1530,
            2640,
            2421,
            1620,
            1213,
            2189,
            2137,
            1701,
            2602,
            2820,
            2710,
            2500,
            1517,
            403,
            2404,
            2303,
            801,
            706,
            2606,
            2341,
            1635,
            2599,
            2082,
            1984,
            1612,
            1610,
            2618,
            1313,
            307,
            2498,
            1987,
            1603,
            2298,
            2156,
            305,
            2211,
            1962,
            1744,
            1725,
            601,
            2581,
            2476,
            2470
        ],
        "skill_5500_5999": [
            2605,
            1627,
            2388,
            2303,
            2645,
            2600,
            2189,
            1620,
            2404,
            1213,
            2820,
            1610,
            2640,
            1530,
            403,
            2599,
            601,
            2560,
            2421,
            2137,
            2341,
            1517,
            1635,
            1701,
            706,
            2500,
            2470,
            1987,
            1715,
            2602,
            1745,
            2606,
            503,
            2710,
            1744,
            1612,
            307,
            1802,
            810,
            2709,
            2708,
            2618,
            1321,
            1621,
            801,
            501,
            2307,
            1313,
            2786,
            1906
        ],
        "skill_6000_6499": [
            2605,
            2303,
            2600,
            1610,
            1627,
            601,
            1213,
            2709,
            1620,
            706,
            2708,
            2640,
            2560,
            2820,
            2388,
            2599,
            910,
            2645,
            2500,
            2404,
            1975,
            1517,
            2319,
            2602,
            1004,
            403,
            307,
            305,
            2134,
            2470,
            1612,
            1530,
            2341,
            1987,
            1701,
            2547,
            2137,
            1217,
            603,
            1802,
            1321,
            604,
            2189,
            1963,
            21,
            2649,
            2421,
            2294,
            501,
            2307
        ],
        "skill_6500_6999": [
            2709,
            2303,
            2605,
            1610,
            2820,
            2708,
            1213,
            2600,
            1620,
            2388,
            2640,
            1612,
            2500,
            2421,
            601,
            1627,
            1741,
            2137,
            403,
            1975,
            2294,
            706,
            910,
            1701,
            2470,
            2134,
            2030,
            2415,
            1802,
            1004,
            2599,
            1621,
            21,
            2527,
            2710,
            1987,
            1429,
            133,
            2703,
            815,
            1206,
            2341,
            2404,
            2227,
            603,
            2319,
            810,
            2560,
            2788,
            1745
        ],
        "skill_7000_7499": [
            2709,
            2820,
            2388,
            2303,
            1610,
            1612,
            1620,
            403,
            2708,
            2421,
            1741,
            910,
            2600,
            1004,
            2294,
            2470,
            1987,
            2605,
            2710,
            2640,
            2415,
            2500,
            1745,
            706,
            133,
            21,
            2030,
            1701,
            1204,
            2703,
            1621,
            2599,
            1517,
            1802,
            2319,
            1843,
            2472,
            2134,
            1975,
            1010,
            810,
            2341,
            2175,
            2137,
            2734,
            1217,
            815,
            805,
            305,
            2413
        ],
        "skill_7500_7999": [
            2388,
            2820,
            1612,
            1004,
            2709,
            2294,
            1610,
            1620,
            2470,
            403,
            1987,
            1938,
            810,
            2303,
            1630,
            2341,
            1517,
            1217,
            1621,
            2001,
            1741,
            2472,
            1728,
            2175,
            133,
            2421,
            1843,
            2703,
            2627,
            1745,
            1744,
            614,
            2404,
            621,
            2199,
            1724,
            1838,
            2500,
            1204,
            2797,
            2710,
            2413,
            1802,
            2734,
            2649,
            2600,
            2581,
            2553,
            2640,
            2672
        ],
        "skill_8000_8499": [
            1612,
            2294,
            2820,
            2341,
            1004,
            2388,
            1620,
            810,
            1938,
            1630,
            1728,
            1517,
            1217,
            2303,
            403,
            614,
            2581,
            1987,
            2001,
            1610,
            1621,
            2627,
            1843,
            2082,
            1724,
            1744,
            1802,
            2199,
            2236,
            2798,
            2797,
            2579,
            2175,
            2470,
            2121,
            1741,
            1600,
            2547,
            621,
            133,
            2553,
            2500,
            1027,
            2649,
            2421,
            2660,
            2307,
            2648,
            2794,
            2404
        ],
        "skill_8500_9999": [
            2341,
            2294,
            2082,
            1517,
            2581,
            1612,
            1938,
            1600,
            810,
            1630,
            1843,
            403,
            1802,
            1728,
            2579,
            1987,
            1004,
            2236,
            1621,
            2547,
            2303,
            1962,
            1744,
            2121,
            1217,
            1620,
            2820,
            1831,
            1724,
            2476,
            2726,
            2404,
            2663,
            2001,
            614,
            2432,
            2005,
            2410,
            1838,
            1213,
            2706,
            1027,
            2798,
            2627,
            2586,
            2566,
            2199,
            2648,
            2227,
            2686
        ],
        "total": [
            1620,
            2966,
            2871,
            2960,
            2968,
            1701,
            2341,
            2865,
            2972,
            2820,
            920,
            2421,
            1422,
            1612,
            2404,
            2977,
            403,
            1627,
            2388,
            1517,
            1630,
            2870,
            2730,
            2961,
            810,
            2974,
            2624,
            2500,
            2236,
            1603,
            2971,
            2709,
            1621,
            2294,
            1829,
            2980,
            1008,
            2978,
            2498,
            1213,
            2691,
            2560,
            2892,
            2584,
            2979,
            2959,
            2853,
            1744,
            1530,
            1506
        ],
        "original": [
            1620,
            2871,
            1701,
            2341,
            2865,
            920,
            2421,
            1422,
            1612,
            2404,
            403,
            1627,
            2388,
            1630,
            2870,
            810,
            2624,
            2500,
            2236,
            1603,
            2709,
            1621,
            2294,
            1829,
            1008,
            2498,
            1213,
            2560,
            2892,
            2584,
            2853,
            1744,
            1506,
            1802,
            2627,
            2414,
            1728,
            2894,
            2189,
            2710,
            2303,
            1715,
            2912,
            2877,
            2762,
            1938,
            2559,
            1745,
            2121,
            1838
        ],
        "bemani": [
            2960,
            2972,
            2977,
            1517,
            2961,
            2974,
            2971,
            2980,
            2978,
            2979,
            2959,
            1530,
            2912,
            2547,
            2973,
            2888,
            2082,
            2255,
            2879,
            2137,
            2598,
            2659,
            2112,
            2915,
            2540,
            2532,
            2816,
            2649,
            2637,
            2111,
            2768,
            1987,
            2663,
            1868,
            2258,
            2976,
            1843,
            2470,
            2636,
            2256,
            2734,
            1983,
            2883,
            2889,
            2798,
            2566,
            2680,
            2962,
            2655,
            1221
        ],
        "famous": [
            2966,
            2968,
            2820,
            2730,
            2691,
            2645,
            2640,
            1846,
            2399,
            2629,
            929,
            2535,
            1235,
            517,
            2085,
            734,
            2177,
            2618,
            1542,
            1147,
            1952,
            1648,
            626,
            2091,
            1940,
            934,
            1951,
            1848,
            828,
            1445,
            1034,
            1845,
            1038,
            1943,
            1847,
            1752,
            120,
            1241,
            731,
            1037,
            2084,
            1345,
            628,
            2088,
            2086,
            5034,
            1850,
            1758,
            1440,
            1236
        ],
        "anime": [
            2820,
            2645,
            1846,
            2399,
            1235,
            2085,
            734,
            2177,
            1542,
            1952,
            1940,
            1951,
            1847,
            1752,
            2084,
            2088,
            2086,
            1850,
            1946,
            1953,
            1040,
            2087,
            2090,
            2089,
            2092,
            1851
        ],
        "band": [
            2820,
            2404,
            2640,
            2399,
            929,
            2579,
            1235,
            734,
            2650,
            2618,
            2648,
            2675,
            2305,
            1147,
            1648,
            626,
            1940,
            934,
            2789,
            1951,
            1848,
            2812,
            828,
            1034,
            1943,
            1752,
            2791,
            2794,
            2792,
            2790,
            1241,
            731,
            2788,
            2785,
            1037,
            2784,
            2086,
            2786,
            2795,
            2793,
            2787,
            1946,
            2296,
            1953,
            2090,
            2089,
            1944,
            1851
        ],
        "western": [
            2413,
            2429,
            2761,
            2493,
            1406,
            2555,
            2296,
            515
        ]
    },
    "general_term": [
        {
            "type": "general_guitar_controller_reward",
            "term": 1,
            "state": 0,
            "start_date": "2021-07-16 10:00:00",
            "end_date": "292278994-08-17 08:",
            "start_date_ms": 1626397200000,
            "end_date_ms": 9223372036825200000
        }
    ],
    "event_list": [
        {
            "data_id": 8,
            "data_version": 200,
            "event_id": 0,
            "event_type": 18,
            "start_date": 1615510800000,
            "end_date": 4771493999000,
            "is_open": true,
            "bg_no": 0,
            "target_musicid": [
                -1,
                -1,
                -1,
                -1,
                -1,
                -1,
                -1,
                -1,
                -1,
                -1
            ],
            "clear_border": 2,
            "reward_musicid": [
                -1,
                -1,
                2708,
                2709
            ],
            "reward_stickerid": -1,
            "firstbit": 0,
            "event_skill_id": 0,
            "quest_no": 0,
            "url": ""
        },
        {
            "data_id": 9,
            "data_version": 200,
            "event_id": 0,
            "event_type": 18,
            "start_date": 1618966800000,
            "end_date": 4771493999000,
            "is_open": true,
            "bg_no": 0,
            "target_musicid": [
                -1,
                -1,
                -1,
                -1,
                -1,
                -1,
                -1,
                -1,
                -1,
                -1
            ],
            "clear_border": 2,
            "reward_musicid": [
                -1,
                -1,
                -1,
                2710
            ],
            "reward_stickerid": -1,
            "firstbit": 0,
            "event_skill_id": 0,
            "quest_no": 0,
            "url": ""
        }
    ]
}