{
    "ranking": {
        "skill_0_999": [
            1530,
            1627,
            5043,
            2238,
            5039,
            5001,
            21,
            1422,
            734,
            5000,
            2730,
            1517,
            929,
            305,
            5078,
            5071,
            5002,
            2618,
            2609,
            2540,
            2443,
            2293,
            2137,
            1802,
            1757,
            1725,
            1618,
            1600,
            1345,
            1321,
            1314,
            1235,
            1206,
            822,
            726,
            718,
            621,
            603,
            600,
            129,
            120,
            110,
            5089,
            5083,
            5076,
            5067,
            5062,
            5059,
            5051,
            5037
        ],
        "skill_1000_1499": [
            2645,
            2605,
            2421,
            2730,
            2710,
            2709,
            2708,
            2399,
            2362,
            2085,
            1984,
            1952,
            1846,
            726,
            621,
            2820,
            2470,
            2303,
            2236,
            2177,
            2156,
            1965,
            1964,
            1648,
            1235,
            1217,
            1129,
            926,
            908,
            836,
            722,
            601,
            2640,
            2566,
            2472,
            2415,
            2404,
            2388,
            2382,
            2373,
            2238,
            2227,
            2137,
            2096,
            2091,
            1933,
            1869,
            1848,
            1721,
            1701
        ],
        "skill_1500_1999": [
            2238,
            601,
            2605,
            2319,
            2709,
            2388,
            2382,
            1984,
            1965,
            1530,
            2710,
            2708,
            2566,
            2415,
            2362,
            2239,
            1721,
            1305,
            738,
            2645,
            2618,
            2602,
            2465,
            2177,
            2134,
            2096,
            2082,
            1951,
            1940,
            1740,
            1725,
            1648,
            1542,
            1403,
            1129,
            1105,
            926,
            709,
            517,
            133,
            21,
            2734,
            2730,
            2560,
            2470,
            2443,
            2442,
            2413,
            2412,
            2410
        ],
        "skill_2000_2499": [
            2708,
            2709,
            2522,
            2382,
            1530,
            2640,
            2238,
            2710,
            2600,
            2443,
            2421,
            517,
            2820,
            2618,
            2430,
            2404,
            2388,
            1403,
            836,
            606,
            207,
            2605,
            2602,
            2527,
            2474,
            2415,
            2239,
            1940,
            1635,
            1542,
            1204,
            960,
            2476,
            2410,
            2362,
            2177,
            2156,
            2137,
            2127,
            1964,
            1847,
            1846,
            1845,
            1725,
            601,
            2730,
            2540,
            2487,
            2468,
            2428
        ],
        "skill_2500_2999": [
            2421,
            2709,
            2605,
            2581,
            2602,
            1627,
            1530,
            2710,
            1963,
            207,
            2382,
            1962,
            910,
            804,
            2708,
            2702,
            2487,
            2470,
            2404,
            2388,
            2238,
            2137,
            2127,
            1517,
            960,
            805,
            601,
            2645,
            2476,
            2307,
            1975,
            1956,
            1008,
            621,
            501,
            2730,
            2606,
            2600,
            2560,
            2559,
            2540,
            2468,
            2465,
            2443,
            2189,
            2082,
            2025,
            836,
            704,
            517
        ],
        "skill_3000_3499": [
            1530,
            2709,
            2602,
            2238,
            2421,
            2708,
            2605,
            1129,
            2189,
            2137,
            1715,
            722,
            717,
            2710,
            2443,
            2388,
            1627,
            2127,
            1620,
            2362,
            1701,
            2645,
            2640,
            2566,
            2476,
            1965,
            805,
            801,
            307,
            2522,
            2465,
            2404,
            1519,
            910,
            2820,
            1984,
            1846,
            1429,
            1008,
            836,
            514,
            403,
            2498,
            2470,
            2442,
            2399,
            2382,
            1952,
            960,
            517
        ],
        "skill_3500_3999": [
            2710,
            1701,
            1530,
            2602,
            2566,
            2421,
            2605,
            2600,
            2137,
            1715,
            2820,
            2708,
            2500,
            2709,
            717,
            1620,
            1429,
            2645,
            2640,
            2606,
            403,
            2581,
            1963,
            1517,
            1213,
            2599,
            2470,
            2465,
            2341,
            1984,
            1217,
            910,
            2498,
            1965,
            722,
            2733,
            2404,
            2388,
            2189,
            1635,
            805,
            709,
            2702,
            2618,
            2442,
            1105,
            917,
            21,
            2560,
            2423
        ],
        "skill_4000_4499": [
            2605,
            1530,
            2710,
            1701,
            1715,
            2566,
            2581,
            2602,
            2421,
            2645,
            1517,
            2500,
            1984,
            2600,
            2560,
            2388,
            2341,
            2189,
            2709,
            2238,
            1627,
            403,
            2708,
            2465,
            1008,
            717,
            2640,
            2442,
            2382,
            305,
            2156,
            1620,
            2606,
            2443,
            1963,
            1429,
            1105,
            2599,
            1213,
            2820,
            2702,
            2404,
            2082,
            2498,
            2298,
            2137,
            1725,
            1635,
            836,
            722
        ],
        "skill_4500_4999": [
            2605,
            1530,
            1627,
            2500,
            2600,
            1213,
            1715,
            2645,
            2421,
            1701,
            2560,
            1620,
            403,
            2710,
            2137,
            2606,
            2581,
            2082,
            2640,
            2602,
            2566,
            2498,
            2476,
            1517,
            2388,
            2341,
            1635,
            305,
            2189,
            801,
            307,
            2820,
            2618,
            601,
            2599,
            2382,
            1987,
            1008,
            1984,
            1802,
            1728,
            2442,
            1725,
            1217,
            2584,
            2134,
            1603,
            501,
            2238,
            1612
        ],
        "skill_5000_5499": [
            2605,
            2560,
            1627,
            1530,
            2388,
            2645,
            2602,
            2600,
            1715,
            2421,
            2189,
            2500,
            1701,
            2710,
            2640,
            1213,
            1620,
            2137,
            403,
            2820,
            2341,
            2303,
            1517,
            706,
            2599,
            2476,
            1612,
            2404,
            1744,
            2606,
            2498,
            2082,
            501,
            2298,
            1635,
            801,
            2708,
            2618,
            1984,
            601,
            2156,
            1725,
            1610,
            305,
            1603,
            2470,
            1987,
            307,
            2522,
            2382
        ],
        "skill_5500_5999": [
            2605,
            1627,
            2645,
            2388,
            2303,
            2189,
            2600,
            2560,
            1530,
            2820,
            2404,
            1620,
            2640,
            601,
            2599,
            1610,
            2710,
            1213,
            2709,
            2500,
            2421,
            1635,
            403,
            2137,
            2470,
            1701,
            2602,
            2341,
            1715,
            2708,
            1517,
            2298,
            706,
            2307,
            1987,
            1802,
            1603,
            1621,
            307,
            1321,
            1313,
            1008,
            305,
            1975,
            1745,
            1612,
            1741,
            2606,
            2476,
            2134
        ],
        "skill_6000_6499": [
            2605,
            2303,
            2600,
            2709,
            2708,
            1627,
            1610,
            1213,
            601,
            706,
            2560,
            2500,
            2388,
            1620,
            2820,
            2640,
            910,
            1975,
            2645,
            1701,
            1530,
            2602,
            2599,
            2319,
            403,
            2421,
            2404,
            603,
            305,
            2527,
            2189,
            2137,
            2134,
            1741,
            1603,
            1004,
            1987,
            1517,
            307,
            1802,
            617,
            2307,
            21,
            604,
            2470,
            1612,
            1963,
            1715,
            1217,
            2710
        ],
        "skill_6500_6999": [
            2709,
            2303,
            2708,
            1610,
            2605,
            2388,
            2500,
            1213,
            2820,
            2600,
            2421,
            2137,
            1620,
            601,
            910,
            2294,
            1612,
            2640,
            1627,
            2710,
            2560,
            2415,
            1741,
            403,
            706,
            2470,
            1975,
            1004,
            2703,
            1701,
            2527,
            133,
            2030,
            1621,
            1429,
            305,
            2734,
            1802,
            2599,
            2134,
            1603,
            307,
            2701,
            810,
            2404,
            2227,
            1630,
            1217,
            815,
            603
        ],
        "skill_7000_7499": [
            2709,
            2388,
            2820,
            2303,
            1610,
            2708,
            1612,
            1620,
            910,
            2294,
            2710,
            2703,
            2600,
            1741,
            2415,
            2421,
            1987,
            1004,
            2734,
            2500,
            403,
            2605,
            2470,
            1745,
            1204,
            2640,
            1701,
            2030,
            1517,
            1010,
            2599,
            1802,
            133,
            2413,
            1843,
            706,
            2134,
            805,
            2701,
            2341,
            514,
            2137,
            305,
            2472,
            2175,
            1217,
            2319,
            810,
            1206,
            21
        ],
        "skill_7500_7999": [
            2388,
            2709,
            1612,
            2820,
            1004,
            2294,
            1610,
            1620,
            2470,
            1938,
            1987,
            403,
            810,
            1630,
            2341,
            1517,
            2472,
            2175,
            1217,
            1728,
            2303,
            1621,
            2001,
            1741,
            2703,
            133,
            614,
            2421,
            1744,
            2710,
            2553,
            2500,
            621,
            1802,
            1745,
            2734,
            1843,
            2404,
            1724,
            617,
            2430,
            2199,
            2797,
            2581,
            2672,
            2627,
            753,
            2307,
            1204,
            805
        ],
        "skill_8000_8499": [
            1612,
            2341,
            2294,
            2820,
            1630,
            1004,
            2388,
            1938,
            1620,
            1728,
            1217,
            810,
            614,
            2581,
            1621,
            2303,
            403,
            1517,
            2082,
            2001,
            1843,
            1724,
            1610,
            1987,
            1744,
            2236,
            1802,
            2199,
            2579,
            1600,
            2500,
            2553,
            2307,
            2627,
            2175,
            133,
            2121,
            2798,
            2797,
            2547,
            2430,
            2404,
            1721,
            2470,
            1027,
            621,
            2702,
            2660,
            2583,
            1603
        ],
        "skill_8500_9999": [
            2341,
            2294,
            2082,
            1612,
            1517,
            1600,
            2581,
            1630,
            1938,
            810,
            1728,
            2579,
            403,
            1802,
            1843,
            2236,
            1004,
            1621,
            1987,
            2303,
            2547,
            1962,
            1217,
            2476,
            1620,
            1744,
            2121,
            2432,
            2820,
            2726,
            1724,
            614,
            1831,
            2404,
            2586,
            2001,
            1838,
            1213,
            1027,
            2410,
            2706,
            2333,
            2227,
            2733,
            2660,
            2568,
            2798,
            2566,
            2005,
            2702
        ],
        "total": [
            1620,
            2820,
            718,
            1701,
            2341,
            2730,
            403,
            1422,
            2189,
            1612,
            2388,
            2421,
            1627,
            1630,
            920,
            1739,
            1517,
            1610,
            1530,
            2476,
            1008,
            2404,
            1603,
            1745,
            1802,
            810,
            2500,
            1715,
            2303,
            1213,
            2709,
            2236,
            1704,
            1004,
            1621,
            2710,
            1744,
            2757,
            2470,
            1741,
            2307,
            2163,
            2498,
            1938,
            2399,
            1834,
            2645,
            2294,
            2584,
            1111
        ],
        "original": [
            1620,
            718,
            1701,
            2341,
            403,
            1422,
            2189,
            1612,
            2388,
            2421,
            1627,
            1630,
            920,
            1739,
            1610,
            2476,
            1008,
            2404,
            1603,
            1745,
            1802,
            810,
            2500,
            1715,
            2303,
            1213,
            2709,
            2236,
            1704,
            1004,
            1621,
            2710,
            1744,
            2757,
            1741,
            2307,
            2163,
            2498,
            1938,
            1834,
            2294,
            2584,
            1111,
            805,
            619,
            2121,
            1838,
            2115,
            1506,
            2238
        ],
        "bemani": [
            1517,
            1530,
            2470,
            2082,
            2137,
            1987,
            1868,
            2598,
            2547,
            2566,
            2540,
            2210,
            1843,
            1429,
            2649,
            2330,
            1982,
            2465,
            2174,
            2659,
            2316,
            2156,
            2458,
            1962,
            722,
            2768,
            2822,
            2734,
            2680,
            2655,
            2430,
            1975,
            2362,
            2632,
            2080,
            1963,
            1984,
            2390,
            2281,
            1223,
            2590,
            1965,
            2835,
            2158,
            2077,
            2699,
            951,
            839,
            1906,
            2512
        ],
        "famous": [
            2820,
            2730,
            2399,
            2645,
            2640,
            734,
            2177,
            1757,
            2618,
            1440,
            1235,
            929,
            1031,
            1342,
            2085,
            1846,
            517,
            1947,
            1147,
            1648,
            1952,
            1940,
            1038,
            626,
            2091,
            1034,
            731,
            1848,
            1445,
            1345,
            1951,
            1847,
            2088,
            828,
            1542,
            934,
            1755,
            1037,
            1845,
            827,
            120,
            2087,
            2084,
            628,
            1943,
            1853,
            1040,
            5034,
            2092,
            624
        ],
        "anime": [
            2820,
            2399,
            2645,
            734,
            2177,
            1235,
            2085,
            1846,
            1952,
            1940,
            1951,
            1847,
            2088,
            1542,
            2087,
            2084,
            1040,
            2092,
            1953,
            2090,
            1946,
            1850,
            2089,
            1851
        ],
        "band": [
            2820,
            2404,
            2399,
            2640,
            734,
            2618,
            1235,
            929,
            2579,
            1147,
            1648,
            2648,
            1940,
            626,
            1034,
            731,
            1848,
            1951,
            828,
            934,
            2650,
            1037,
            2305,
            2789,
            2792,
            2794,
            2791,
            1943,
            2790,
            2784,
            2785,
            1953,
            2090,
            2788,
            2786,
            1946,
            2795,
            2296,
            2787,
            2089,
            1851,
            2793
        ],
        "western": [
            2413,
            2429,
            2493,
            2555,
            2296,
            1406,
            515
        ]
    },
    "general_term": [
        {
            "type": "general_guitar_controller_reward",
            "term": 1,
            "state": 0,
            "start_date": "2021-07-16 10:00:00",
            "end_date": "292278994-08-17 08:",
            "start_date_ms": 1626397200000,
            "end_date_ms": 9223372036825200000
        }
    ],
    "event_list": [
        {
            "data_id": 8,
            "data_version": 200,
            "event_id": 0,
            "event_type": 18,
            "start_date": 1615510800000,
            "end_date": 9223372036825200000,
            "is_open": true,
            "bg_no": 0,
            "target_musicid": [
                -1,
                -1,
                -1,
                -1,
                -1,
                -1,
                -1,
                -1,
                -1,
                -1
            ],
            "clear_border": 2,
            "reward_musicid": [
                -1,
                -1,
                2708,
                2709
            ],
            "reward_stickerid": -1,
            "firstbit": 0,
            "event_skill_id": 0,
            "quest_no": 0,
            "url": ""
        },
        {
            "data_id": 9,
            "data_version": 200,
            "event_id": 0,
            "event_type": 18,
            "start_date": 1618966800000,
            "end_date": 9223372036825200000,
            "is_open": true,
            "bg_no": 0,
            "target_musicid": [
                -1,
                -1,
                -1,
                -1,
                -1,
                -1,
                -1,
                -1,
                -1,
                -1
            ],
            "clear_border": 2,
            "reward_musicid": [
                -1,
                -1,
                -1,
                2710
            ],
            "reward_stickerid": -1,
            "firstbit": 0,
            "event_skill_id": 0,
            "quest_no": 0,
            "url": ""
        }
    ]
}