[
    {
        "season_id": 1,
        "season_name": "SKILL ANALYZER 第1回",
        "season_new_flg": false,
        "course_id": 1,
        "course_name": "SKILL ANALYZER Level.01",
        "course_type": 0,
        "skill_level": 1,
        "skill_name_id": 1,
        "matching_assist": true,
        "clear_rate": 9206,
        "avg_score": 27230661,
        "tracks": [
            {
                "track_no": 0,
                "music_id": 682,
                "music_type": 0
            },
            {
                "track_no": 1,
                "music_id": 987,
                "music_type": 1
            },
            {
                "track_no": 2,
                "music_id": 756,
                "music_type": 1
            }
        ]
    },
    {
        "season_id": 4,
        "season_name": "SKILL ANALYZER 第2回",
        "season_new_flg": false,
        "course_id": 1,
        "course_name": "SKILL ANALYZER Level.01",
        "course_type": 0,
        "skill_level": 1,
        "skill_name_id": 1,
        "matching_assist": true,
        "clear_rate": 9218,
        "avg_score": 27684682,
        "tracks": [
            {
                "track_no": 0,
                "music_id": 803,
                "music_type": 0
            },
            {
                "track_no": 1,
                "music_id": 334,
                "music_type": 1
            },
            {
                "track_no": 2,
                "music_id": 126,
                "music_type": 0
            }
        ]
    },
    {
        "season_id": 7,
        "season_name": "SKILL ANALYZER 第3回",
        "season_new_flg": false,
        "course_id": 1,
        "course_name": "SKILL ANALYZER Level.01",
        "course_type": 0,
        "skill_level": 1,
        "skill_name_id": 1,
        "matching_assist": true,
        "clear_rate": 8785,
        "avg_score": 26746414,
        "tracks": [
            {
                "track_no": 0,
                "music_id": 816,
                "music_type": 0
            },
            {
                "track_no": 1,
                "music_id": 1074,
                "music_type": 1
            },
            {
                "track_no": 2,
                "music_id": 16,
                "music_type": 1
            }
        ]
    },
    {
        "season_id": 10,
        "season_name": "SKILL ANALYZER 第4回",
        "season_new_flg": true,
        "course_id": 1,
        "course_name": "SKILL ANALYZER Level.01",
        "course_type": 0,
        "skill_level": 1,
        "skill_name_id": 1,
        "matching_assist": true,
        "clear_rate": 9010,
        "avg_score": 27217006,
        "tracks": [
            {
                "track_no": 0,
                "music_id": 1866,
                "music_type": 0
            },
            {
                "track_no": 1,
                "music_id": 1076,
                "music_type": 1
            },
            {
                "track_no": 2,
                "music_id": 6,
                "music_type": 1
            }
        ]
    },
    {
        "season_id": 1,
        "season_name": "SKILL ANALYZER 第1回",
        "season_new_flg": false,
        "course_id": 2,
        "course_name": "SKILL ANALYZER Level.02",
        "course_type": 0,
        "skill_level": 2,
        "skill_name_id": 2,
        "matching_assist": true,
        "clear_rate": 9289,
        "avg_score": 27266966,
        "tracks": [
            {
                "track_no": 0,
                "music_id": 65,
                "music_type": 1
            },
            {
                "track_no": 1,
                "music_id": 614,
                "music_type": 1
            },
            {
                "track_no": 2,
                "music_id": 1002,
                "music_type": 1
            }
        ]
    },
    {
        "season_id": 4,
        "season_name": "SKILL ANALYZER 第2回",
        "season_new_flg": false,
        "course_id": 2,
        "course_name": "SKILL ANALYZER Level.02",
        "course_type": 0,
        "skill_level": 2,
        "skill_name_id": 2,
        "matching_assist": true,
        "clear_rate": 9430,
        "avg_score": 27920468,
        "tracks": [
            {
                "track_no": 0,
                "music_id": 283,
                "music_type": 1
            },
            {
                "track_no": 1,
                "music_id": 181,
                "music_type": 1
            },
            {
                "track_no": 2,
                "music_id": 1079,
                "music_type": 1
            }
        ]
    },
    {
        "season_id": 7,
        "season_name": "SKILL ANALYZER 第3回",
        "season_new_flg": false,
        "course_id": 2,
        "course_name": "SKILL ANALYZER Level.02",
        "course_type": 0,
        "skill_level": 2,
        "skill_name_id": 2,
        "matching_assist": true,
        "clear_rate": 9510,
        "avg_score": 28062586,
        "tracks": [
            {
                "track_no": 0,
                "music_id": 74,
                "music_type": 0
            },
            {
                "track_no": 1,
                "music_id": 1093,
                "music_type": 1
            },
            {
                "track_no": 2,
                "music_id": 561,
                "music_type": 1
            }
        ]
    },
    {
        "season_id": 10,
        "season_name": "SKILL ANALYZER 第4回",
        "season_new_flg": true,
        "course_id": 2,
        "course_name": "SKILL ANALYZER Level.02",
        "course_type": 0,
        "skill_level": 2,
        "skill_name_id": 2,
        "matching_assist": true,
        "clear_rate": 9041,
        "avg_score": 27877275,
        "tracks": [
            {
                "track_no": 0,
                "music_id": 766,
                "music_type": 1
            },
            {
                "track_no": 1,
                "music_id": 1063,
                "music_type": 1
            },
            {
                "track_no": 2,
                "music_id": 42,
                "music_type": 1
            }
        ]
    },
    {
        "season_id": 1,
        "season_name": "SKILL ANALYZER 第1回",
        "season_new_flg": false,
        "course_id": 3,
        "course_name": "SKILL ANALYZER Level.03",
        "course_type": 0,
        "skill_level": 3,
        "skill_name_id": 3,
        "matching_assist": true,
        "clear_rate": 9349,
        "avg_score": 27314623,
        "tracks": [
            {
                "track_no": 0,
                "music_id": 603,
                "music_type": 1
            },
            {
                "track_no": 1,
                "music_id": 799,
                "music_type": 1
            },
            {
                "track_no": 2,
                "music_id": 346,
                "music_type": 1
            }
        ]
    },
    {
        "season_id": 4,
        "season_name": "SKILL ANALYZER 第2回",
        "season_new_flg": false,
        "course_id": 3,
        "course_name": "SKILL ANALYZER Level.03",
        "course_type": 0,
        "skill_level": 3,
        "skill_name_id": 3,
        "matching_assist": true,
        "clear_rate": 8966,
        "avg_score": 27308855,
        "tracks": [
            {
                "track_no": 0,
                "music_id": 860,
                "music_type": 1
            },
            {
                "track_no": 1,
                "music_id": 620,
                "music_type": 1
            },
            {
                "track_no": 2,
                "music_id": 1650,
                "music_type": 1
            }
        ]
    },
    {
        "season_id": 7,
        "season_name": "SKILL ANALYZER 第3回",
        "season_new_flg": false,
        "course_id": 3,
        "course_name": "SKILL ANALYZER Level.03",
        "course_type": 0,
        "skill_level": 3,
        "skill_name_id": 3,
        "matching_assist": true,
        "clear_rate": 8938,
        "avg_score": 27372231,
        "tracks": [
            {
                "track_no": 0,
                "music_id": 1082,
                "music_type": 1
            },
            {
                "track_no": 1,
                "music_id": 783,
                "music_type": 1
            },
            {
                "track_no": 2,
                "music_id": 608,
                "music_type": 1
            }
        ]
    },
    {
        "season_id": 10,
        "season_name": "SKILL ANALYZER 第4回",
        "season_new_flg": true,
        "course_id": 3,
        "course_name": "SKILL ANALYZER Level.03",
        "course_type": 0,
        "skill_level": 3,
        "skill_name_id": 3,
        "matching_assist": true,
        "clear_rate": 9135,
        "avg_score": 27527477,
        "tracks": [
            {
                "track_no": 0,
                "music_id": 353,
                "music_type": 1
            },
            {
                "track_no": 1,
                "music_id": 1294,
                "music_type": 1
            },
            {
                "track_no": 2,
                "music_id": 827,
                "music_type": 1
            }
        ]
    },
    {
        "season_id": 1,
        "season_name": "SKILL ANALYZER 第1回",
        "season_new_flg": false,
        "course_id": 4,
        "course_name": "SKILL ANALYZER Level.04",
        "course_type": 0,
        "skill_level": 4,
        "skill_name_id": 4,
        "matching_assist": true,
        "clear_rate": 9373,
        "avg_score": 27168901,
        "tracks": [
            {
                "track_no": 0,
                "music_id": 497,
                "music_type": 1
            },
            {
                "track_no": 1,
                "music_id": 1021,
                "music_type": 1
            },
            {
                "track_no": 2,
                "music_id": 800,
                "music_type": 1
            }
        ]
    },
    {
        "season_id": 4,
        "season_name": "SKILL ANALYZER 第2回",
        "season_new_flg": false,
        "course_id": 4,
        "course_name": "SKILL ANALYZER Level.04",
        "course_type": 0,
        "skill_level": 4,
        "skill_name_id": 4,
        "matching_assist": true,
        "clear_rate": 8873,
        "avg_score": 27174565,
        "tracks": [
            {
                "track_no": 0,
                "music_id": 969,
                "music_type": 1
            },
            {
                "track_no": 1,
                "music_id": 343,
                "music_type": 1
            },
            {
                "track_no": 2,
                "music_id": 851,
                "music_type": 1
            }
        ]
    },
    {
        "season_id": 7,
        "season_name": "SKILL ANALYZER 第3回",
        "season_new_flg": false,
        "course_id": 4,
        "course_name": "SKILL ANALYZER Level.04",
        "course_type": 0,
        "skill_level": 4,
        "skill_name_id": 4,
        "matching_assist": true,
        "clear_rate": 9184,
        "avg_score": 27321889,
        "tracks": [
            {
                "track_no": 0,
                "music_id": 1444,
                "music_type": 1
            },
            {
                "track_no": 1,
                "music_id": 394,
                "music_type": 1
            },
            {
                "track_no": 2,
                "music_id": 122,
                "music_type": 1
            }
        ]
    },
    {
        "season_id": 10,
        "season_name": "SKILL ANALYZER 第4回",
        "season_new_flg": true,
        "course_id": 4,
        "course_name": "SKILL ANALYZER Level.04",
        "course_type": 0,
        "skill_level": 4,
        "skill_name_id": 4,
        "matching_assist": true,
        "clear_rate": 9224,
        "avg_score": 27918857,
        "tracks": [
            {
                "track_no": 0,
                "music_id": 524,
                "music_type": 1
            },
            {
                "track_no": 1,
                "music_id": 534,
                "music_type": 1
            },
            {
                "track_no": 2,
                "music_id": 858,
                "music_type": 1
            }
        ]
    },
    {
        "season_id": 1,
        "season_name": "SKILL ANALYZER 第1回",
        "season_new_flg": false,
        "course_id": 5,
        "course_name": "SKILL ANALYZER Level.05",
        "course_type": 0,
        "skill_level": 5,
        "skill_name_id": 5,
        "matching_assist": true,
        "clear_rate": 7044,
        "avg_score": 25974259,
        "tracks": [
            {
                "track_no": 0,
                "music_id": 537,
                "music_type": 1
            },
            {
                "track_no": 1,
                "music_id": 403,
                "music_type": 2
            },
            {
                "track_no": 2,
                "music_id": 775,
                "music_type": 2
            }
        ]
    },
    {
        "season_id": 4,
        "season_name": "SKILL ANALYZER 第2回",
        "season_new_flg": false,
        "course_id": 5,
        "course_name": "SKILL ANALYZER Level.05",
        "course_type": 0,
        "skill_level": 5,
        "skill_name_id": 5,
        "matching_assist": true,
        "clear_rate": 6122,
        "avg_score": 23140116,
        "tracks": [
            {
                "track_no": 0,
                "music_id": 392,
                "music_type": 1
            },
            {
                "track_no": 1,
                "music_id": 601,
                "music_type": 2
            },
            {
                "track_no": 2,
                "music_id": 665,
                "music_type": 2
            }
        ]
    },
    {
        "season_id": 7,
        "season_name": "SKILL ANALYZER 第3回",
        "season_new_flg": false,
        "course_id": 5,
        "course_name": "SKILL ANALYZER Level.05",
        "course_type": 0,
        "skill_level": 5,
        "skill_name_id": 5,
        "matching_assist": true,
        "clear_rate": 6780,
        "avg_score": 23347273,
        "tracks": [
            {
                "track_no": 0,
                "music_id": 962,
                "music_type": 1
            },
            {
                "track_no": 1,
                "music_id": 845,
                "music_type": 2
            },
            {
                "track_no": 2,
                "music_id": 66,
                "music_type": 2
            }
        ]
    },
    {
        "season_id": 10,
        "season_name": "SKILL ANALYZER 第4回",
        "season_new_flg": true,
        "course_id": 5,
        "course_name": "SKILL ANALYZER Level.05",
        "course_type": 0,
        "skill_level": 5,
        "skill_name_id": 5,
        "matching_assist": true,
        "clear_rate": 8133,
        "avg_score": 26730090,
        "tracks": [
            {
                "track_no": 0,
                "music_id": 1861,
                "music_type": 1
            },
            {
                "track_no": 1,
                "music_id": 822,
                "music_type": 2
            },
            {
                "track_no": 2,
                "music_id": 207,
                "music_type": 2
            }
        ]
    },
    {
        "season_id": 1,
        "season_name": "SKILL ANALYZER 第1回",
        "season_new_flg": false,
        "course_id": 6,
        "course_name": "SKILL ANALYZER Level.06",
        "course_type": 0,
        "skill_level": 6,
        "skill_name_id": 6,
        "matching_assist": true,
        "clear_rate": 8067,
        "avg_score": 25606799,
        "tracks": [
            {
                "track_no": 0,
                "music_id": 890,
                "music_type": 2
            },
            {
                "track_no": 1,
                "music_id": 891,
                "music_type": 2
            },
            {
                "track_no": 2,
                "music_id": 1423,
                "music_type": 2
            }
        ]
    },
    {
        "season_id": 4,
        "season_name": "SKILL ANALYZER 第2回",
        "season_new_flg": false,
        "course_id": 6,
        "course_name": "SKILL ANALYZER Level.06",
        "course_type": 0,
        "skill_level": 6,
        "skill_name_id": 6,
        "matching_assist": true,
        "clear_rate": 6532,
        "avg_score": 23859939,
        "tracks": [
            {
                "track_no": 0,
                "music_id": 1441,
                "music_type": 2
            },
            {
                "track_no": 1,
                "music_id": 232,
                "music_type": 2
            },
            {
                "track_no": 2,
                "music_id": 1472,
                "music_type": 2
            }
        ]
    },
    {
        "season_id": 7,
        "season_name": "SKILL ANALYZER 第3回",
        "season_new_flg": false,
        "course_id": 6,
        "course_name": "SKILL ANALYZER Level.06",
        "course_type": 0,
        "skill_level": 6,
        "skill_name_id": 6,
        "matching_assist": true,
        "clear_rate": 8593,
        "avg_score": 26912210,
        "tracks": [
            {
                "track_no": 0,
                "music_id": 196,
                "music_type": 2
            },
            {
                "track_no": 1,
                "music_id": 1134,
                "music_type": 2
            },
            {
                "track_no": 2,
                "music_id": 1473,
                "music_type": 2
            }
        ]
    },
    {
        "season_id": 10,
        "season_name": "SKILL ANALYZER 第4回",
        "season_new_flg": true,
        "course_id": 6,
        "course_name": "SKILL ANALYZER Level.06",
        "course_type": 0,
        "skill_level": 6,
        "skill_name_id": 6,
        "matching_assist": true,
        "clear_rate": 8235,
        "avg_score": 26362806,
        "tracks": [
            {
                "track_no": 0,
                "music_id": 1090,
                "music_type": 2
            },
            {
                "track_no": 1,
                "music_id": 331,
                "music_type": 2
            },
            {
                "track_no": 2,
                "music_id": 438,
                "music_type": 2
            }
        ]
    },
    {
        "season_id": 1,
        "season_name": "SKILL ANALYZER 第1回",
        "season_new_flg": false,
        "course_id": 7,
        "course_name": "SKILL ANALYZER Level.07",
        "course_type": 0,
        "skill_level": 7,
        "skill_name_id": 7,
        "matching_assist": true,
        "clear_rate": 8387,
        "avg_score": 27220661,
        "tracks": [
            {
                "track_no": 0,
                "music_id": 784,
                "music_type": 2
            },
            {
                "track_no": 1,
                "music_id": 979,
                "music_type": 2
            },
            {
                "track_no": 2,
                "music_id": 492,
                "music_type": 2
            }
        ]
    },
    {
        "season_id": 4,
        "season_name": "SKILL ANALYZER 第2回",
        "season_new_flg": false,
        "course_id": 7,
        "course_name": "SKILL ANALYZER Level.07",
        "course_type": 0,
        "skill_level": 7,
        "skill_name_id": 7,
        "matching_assist": true,
        "clear_rate": 7622,
        "avg_score": 25236884,
        "tracks": [
            {
                "track_no": 0,
                "music_id": 862,
                "music_type": 2
            },
            {
                "track_no": 1,
                "music_id": 22,
                "music_type": 3
            },
            {
                "track_no": 2,
                "music_id": 519,
                "music_type": 2
            }
        ]
    },
    {
        "season_id": 7,
        "season_name": "SKILL ANALYZER 第3回",
        "season_new_flg": false,
        "course_id": 7,
        "course_name": "SKILL ANALYZER Level.07",
        "course_type": 0,
        "skill_level": 7,
        "skill_name_id": 7,
        "matching_assist": true,
        "clear_rate": 7836,
        "avg_score": 25280152,
        "tracks": [
            {
                "track_no": 0,
                "music_id": 1439,
                "music_type": 2
            },
            {
                "track_no": 1,
                "music_id": 401,
                "music_type": 2
            },
            {
                "track_no": 2,
                "music_id": 134,
                "music_type": 2
            }
        ]
    },
    {
        "season_id": 10,
        "season_name": "SKILL ANALYZER 第4回",
        "season_new_flg": true,
        "course_id": 7,
        "course_name": "SKILL ANALYZER Level.07",
        "course_type": 0,
        "skill_level": 7,
        "skill_name_id": 7,
        "matching_assist": true,
        "clear_rate": 7886,
        "avg_score": 25667407,
        "tracks": [
            {
                "track_no": 0,
                "music_id": 762,
                "music_type": 2
            },
            {
                "track_no": 1,
                "music_id": 843,
                "music_type": 2
            },
            {
                "track_no": 2,
                "music_id": 777,
                "music_type": 2
            }
        ]
    },
    {
        "season_id": 1,
        "season_name": "SKILL ANALYZER 第1回",
        "season_new_flg": false,
        "course_id": 8,
        "course_name": "SKILL ANALYZER Level.08",
        "course_type": 0,
        "skill_level": 8,
        "skill_name_id": 8,
        "matching_assist": false,
        "clear_rate": 8372,
        "avg_score": 26703480,
        "tracks": [
            {
                "track_no": 0,
                "music_id": 878,
                "music_type": 4
            },
            {
                "track_no": 1,
                "music_id": 1155,
                "music_type": 4
            },
            {
                "track_no": 2,
                "music_id": 541,
                "music_type": 2
            }
        ]
    },
    {
        "season_id": 4,
        "season_name": "SKILL ANALYZER 第2回",
        "season_new_flg": false,
        "course_id": 8,
        "course_name": "SKILL ANALYZER Level.08",
        "course_type": 0,
        "skill_level": 8,
        "skill_name_id": 8,
        "matching_assist": false,
        "clear_rate": 7024,
        "avg_score": 25305632,
        "tracks": [
            {
                "track_no": 0,
                "music_id": 622,
                "music_type": 2
            },
            {
                "track_no": 1,
                "music_id": 1562,
                "music_type": 2
            },
            {
                "track_no": 2,
                "music_id": 398,
                "music_type": 2
            }
        ]
    },
    {
        "season_id": 7,
        "season_name": "SKILL ANALYZER 第3回",
        "season_new_flg": false,
        "course_id": 8,
        "course_name": "SKILL ANALYZER Level.08",
        "course_type": 0,
        "skill_level": 8,
        "skill_name_id": 8,
        "matching_assist": false,
        "clear_rate": 7508,
        "avg_score": 24936187,
        "tracks": [
            {
                "track_no": 0,
                "music_id": 898,
                "music_type": 4
            },
            {
                "track_no": 1,
                "music_id": 555,
                "music_type": 2
            },
            {
                "track_no": 2,
                "music_id": 216,
                "music_type": 2
            }
        ]
    },
    {
        "season_id": 10,
        "season_name": "SKILL ANALYZER 第4回",
        "season_new_flg": true,
        "course_id": 8,
        "course_name": "SKILL ANALYZER Level.08",
        "course_type": 0,
        "skill_level": 8,
        "skill_name_id": 8,
        "matching_assist": false,
        "clear_rate": 7073,
        "avg_score": 25153847,
        "tracks": [
            {
                "track_no": 0,
                "music_id": 54,
                "music_type": 3
            },
            {
                "track_no": 1,
                "music_id": 1346,
                "music_type": 2
            },
            {
                "track_no": 2,
                "music_id": 887,
                "music_type": 4
            }
        ]
    },
    {
        "season_id": 1,
        "season_name": "SKILL ANALYZER 第1回",
        "season_new_flg": false,
        "course_id": 9,
        "course_name": "SKILL ANALYZER Level.09",
        "course_type": 0,
        "skill_level": 9,
        "skill_name_id": 9,
        "matching_assist": false,
        "clear_rate": 8146,
        "avg_score": 25725153,
        "tracks": [
            {
                "track_no": 0,
                "music_id": 1306,
                "music_type": 2
            },
            {
                "track_no": 1,
                "music_id": 1309,
                "music_type": 2
            },
            {
                "track_no": 2,
                "music_id": 802,
                "music_type": 2
            }
        ]
    },
    {
        "season_id": 4,
        "season_name": "SKILL ANALYZER 第2回",
        "season_new_flg": false,
        "course_id": 9,
        "course_name": "SKILL ANALYZER Level.09",
        "course_type": 0,
        "skill_level": 9,
        "skill_name_id": 9,
        "matching_assist": false,
        "clear_rate": 6798,
        "avg_score": 24854502,
        "tracks": [
            {
                "track_no": 0,
                "music_id": 1563,
                "music_type": 3
            },
            {
                "track_no": 1,
                "music_id": 120,
                "music_type": 3
            },
            {
                "track_no": 2,
                "music_id": 581,
                "music_type": 2
            }
        ]
    },
    {
        "season_id": 7,
        "season_name": "SKILL ANALYZER 第3回",
        "season_new_flg": false,
        "course_id": 9,
        "course_name": "SKILL ANALYZER Level.09",
        "course_type": 0,
        "skill_level": 9,
        "skill_name_id": 9,
        "matching_assist": false,
        "clear_rate": 8008,
        "avg_score": 26299543,
        "tracks": [
            {
                "track_no": 0,
                "music_id": 1065,
                "music_type": 4
            },
            {
                "track_no": 1,
                "music_id": 1568,
                "music_type": 3
            },
            {
                "track_no": 2,
                "music_id": 493,
                "music_type": 3
            }
        ]
    },
    {
        "season_id": 10,
        "season_name": "SKILL ANALYZER 第4回",
        "season_new_flg": true,
        "course_id": 9,
        "course_name": "SKILL ANALYZER Level.09",
        "course_type": 0,
        "skill_level": 9,
        "skill_name_id": 9,
        "matching_assist": false,
        "clear_rate": 6339,
        "avg_score": 25941725,
        "tracks": [
            {
                "track_no": 0,
                "music_id": 1442,
                "music_type": 4
            },
            {
                "track_no": 1,
                "music_id": 1092,
                "music_type": 4
            },
            {
                "track_no": 2,
                "music_id": 348,
                "music_type": 2
            }
        ]
    },
    {
        "season_id": 1,
        "season_name": "SKILL ANALYZER 第1回",
        "season_new_flg": false,
        "course_id": 10,
        "course_name": "SKILL ANALYZER Level.10",
        "course_type": 0,
        "skill_level": 10,
        "skill_name_id": 10,
        "matching_assist": false,
        "clear_rate": 8437,
        "avg_score": 26559931,
        "tracks": [
            {
                "track_no": 0,
                "music_id": 847,
                "music_type": 2
            },
            {
                "track_no": 1,
                "music_id": 716,
                "music_type": 2
            },
            {
                "track_no": 2,
                "music_id": 615,
                "music_type": 2
            }
        ]
    },
    {
        "season_id": 4,
        "season_name": "SKILL ANALYZER 第2回",
        "season_new_flg": false,
        "course_id": 10,
        "course_name": "SKILL ANALYZER Level.10",
        "course_type": 0,
        "skill_level": 10,
        "skill_name_id": 10,
        "matching_assist": false,
        "clear_rate": 8540,
        "avg_score": 25749743,
        "tracks": [
            {
                "track_no": 0,
                "music_id": 139,
                "music_type": 3
            },
            {
                "track_no": 1,
                "music_id": 1552,
                "music_type": 3
            },
            {
                "track_no": 2,
                "music_id": 834,
                "music_type": 4
            }
        ]
    },
    {
        "season_id": 7,
        "season_name": "SKILL ANALYZER 第3回",
        "season_new_flg": false,
        "course_id": 10,
        "course_name": "SKILL ANALYZER Level.10",
        "course_type": 0,
        "skill_level": 10,
        "skill_name_id": 10,
        "matching_assist": false,
        "clear_rate": 8212,
        "avg_score": 26544343,
        "tracks": [
            {
                "track_no": 0,
                "music_id": 1081,
                "music_type": 4
            },
            {
                "track_no": 1,
                "music_id": 508,
                "music_type": 2
            },
            {
                "track_no": 2,
                "music_id": 251,
                "music_type": 3
            }
        ]
    },
    {
        "season_id": 10,
        "season_name": "SKILL ANALYZER 第4回",
        "season_new_flg": true,
        "course_id": 10,
        "course_name": "SKILL ANALYZER Level.10",
        "course_type": 0,
        "skill_level": 10,
        "skill_name_id": 10,
        "matching_assist": false,
        "clear_rate": 9010,
        "avg_score": 27570276,
        "tracks": [
            {
                "track_no": 0,
                "music_id": 426,
                "music_type": 3
            },
            {
                "track_no": 1,
                "music_id": 361,
                "music_type": 3
            },
            {
                "track_no": 2,
                "music_id": 1348,
                "music_type": 3
            }
        ]
    },
    {
        "season_id": 5,
        "season_name": "SKILL ANALYZER 第2回 Aコース",
        "season_new_flg": false,
        "course_id": 11,
        "course_name": "SKILL ANALYZER Level.11",
        "course_type": 3,
        "skill_level": 11,
        "skill_name_id": 11,
        "matching_assist": false,
        "clear_rate": 8004,
        "avg_score": 25419487,
        "tracks": [
            {
                "track_no": 0,
                "music_id": 1558,
                "music_type": 3
            },
            {
                "track_no": 1,
                "music_id": 1775,
                "music_type": 4
            },
            {
                "track_no": 2,
                "music_id": 1096,
                "music_type": 4
            }
        ]
    },
    {
        "season_id": 6,
        "season_name": "SKILL ANALYZER 第2回 Bコース",
        "season_new_flg": false,
        "course_id": 11,
        "course_name": "SKILL ANALYZER Level.11",
        "course_type": 3,
        "skill_level": 11,
        "skill_name_id": 11,
        "matching_assist": false,
        "clear_rate": 7630,
        "avg_score": 25135563,
        "tracks": [
            {
                "track_no": 0,
                "music_id": 1072,
                "music_type": 4
            },
            {
                "track_no": 1,
                "music_id": 1779,
                "music_type": 4
            },
            {
                "track_no": 2,
                "music_id": 1554,
                "music_type": 3
            }
        ]
    },
    {
        "season_id": 8,
        "season_name": "SKILL ANALYZER 第3回 Aコース",
        "season_new_flg": false,
        "course_id": 11,
        "course_name": "SKILL ANALYZER Level.11",
        "course_type": 3,
        "skill_level": 11,
        "skill_name_id": 11,
        "matching_assist": false,
        "clear_rate": 8083,
        "avg_score": 26010290,
        "tracks": [
            {
                "track_no": 0,
                "music_id": 1901,
                "music_type": 4
            },
            {
                "track_no": 1,
                "music_id": 1797,
                "music_type": 4
            },
            {
                "track_no": 2,
                "music_id": 642,
                "music_type": 2
            }
        ]
    },
    {
        "season_id": 9,
        "season_name": "SKILL ANALYZER 第3回 Bコース",
        "season_new_flg": false,
        "course_id": 11,
        "course_name": "SKILL ANALYZER Level.11",
        "course_type": 3,
        "skill_level": 11,
        "skill_name_id": 11,
        "matching_assist": false,
        "clear_rate": 8512,
        "avg_score": 26471716,
        "tracks": [
            {
                "track_no": 0,
                "music_id": 1011,
                "music_type": 4
            },
            {
                "track_no": 1,
                "music_id": 1782,
                "music_type": 4
            },
            {
                "track_no": 2,
                "music_id": 1899,
                "music_type": 4
            }
        ]
    },
    {
        "season_id": 11,
        "season_name": "SKILL ANALYZER 第4回 Aコース",
        "season_new_flg": true,
        "course_id": 11,
        "course_name": "SKILL ANALYZER Level.11",
        "course_type": 3,
        "skill_level": 11,
        "skill_name_id": 11,
        "matching_assist": false,
        "clear_rate": 7584,
        "avg_score": 25532644,
        "tracks": [
            {
                "track_no": 0,
                "music_id": 2050,
                "music_type": 4
            },
            {
                "track_no": 1,
                "music_id": 2043,
                "music_type": 4
            },
            {
                "track_no": 2,
                "music_id": 1865,
                "music_type": 4
            }
        ]
    },
    {
        "season_id": 12,
        "season_name": "SKILL ANALYZER 第4回 Bコース",
        "season_new_flg": true,
        "course_id": 11,
        "course_name": "SKILL ANALYZER Level.11",
        "course_type": 3,
        "skill_level": 11,
        "skill_name_id": 11,
        "matching_assist": false,
        "clear_rate": 8186,
        "avg_score": 26118375,
        "tracks": [
            {
                "track_no": 0,
                "music_id": 2049,
                "music_type": 4
            },
            {
                "track_no": 1,
                "music_id": 831,
                "music_type": 3
            },
            {
                "track_no": 2,
                "music_id": 1995,
                "music_type": 4
            }
        ]
    },
    {
        "season_id": 5,
        "season_name": "SKILL ANALYZER 第2回 Aコース",
        "season_new_flg": false,
        "course_id": 12,
        "course_name": "SKILL ANALYZER Level.∞",
        "course_type": 3,
        "skill_level": 12,
        "skill_name_id": 12,
        "matching_assist": false,
        "clear_rate": 5438,
        "avg_score": 24351590,
        "tracks": [
            {
                "track_no": 0,
                "music_id": 636,
                "music_type": 3
            },
            {
                "track_no": 1,
                "music_id": 367,
                "music_type": 3
            },
            {
                "track_no": 2,
                "music_id": 1766,
                "music_type": 4
            }
        ]
    },
    {
        "season_id": 6,
        "season_name": "SKILL ANALYZER 第2回 Bコース",
        "season_new_flg": false,
        "course_id": 12,
        "course_name": "SKILL ANALYZER Level.∞",
        "course_type": 3,
        "skill_level": 12,
        "skill_name_id": 12,
        "matching_assist": false,
        "clear_rate": 5745,
        "avg_score": 24177900,
        "tracks": [
            {
                "track_no": 0,
                "music_id": 1769,
                "music_type": 4
            },
            {
                "track_no": 1,
                "music_id": 1768,
                "music_type": 4
            },
            {
                "track_no": 2,
                "music_id": 1767,
                "music_type": 4
            }
        ]
    },
    {
        "season_id": 8,
        "season_name": "SKILL ANALYZER 第3回 Aコース",
        "season_new_flg": false,
        "course_id": 12,
        "course_name": "SKILL ANALYZER Level.∞",
        "course_type": 3,
        "skill_level": 12,
        "skill_name_id": 12,
        "matching_assist": false,
        "clear_rate": 5710,
        "avg_score": 24856832,
        "tracks": [
            {
                "track_no": 0,
                "music_id": 360,
                "music_type": 3
            },
            {
                "track_no": 1,
                "music_id": 1894,
                "music_type": 4
            },
            {
                "track_no": 2,
                "music_id": 1888,
                "music_type": 4
            }
        ]
    },
    {
        "season_id": 9,
        "season_name": "SKILL ANALYZER 第3回 Bコース",
        "season_new_flg": false,
        "course_id": 12,
        "course_name": "SKILL ANALYZER Level.∞",
        "course_type": 3,
        "skill_level": 12,
        "skill_name_id": 12,
        "matching_assist": false,
        "clear_rate": 5331,
        "avg_score": 24116321,
        "tracks": [
            {
                "track_no": 0,
                "music_id": 1893,
                "music_type": 4
            },
            {
                "track_no": 1,
                "music_id": 1674,
                "music_type": 4
            },
            {
                "track_no": 2,
                "music_id": 1889,
                "music_type": 4
            }
        ]
    },
    {
        "season_id": 11,
        "season_name": "SKILL ANALYZER 第4回 Aコース",
        "season_new_flg": true,
        "course_id": 12,
        "course_name": "SKILL ANALYZER Level.∞",
        "course_type": 3,
        "skill_level": 12,
        "skill_name_id": 12,
        "matching_assist": false,
        "clear_rate": 6956,
        "avg_score": 26385527,
        "tracks": [
            {
                "track_no": 0,
                "music_id": 374,
                "music_type": 3
            },
            {
                "track_no": 1,
                "music_id": 2039,
                "music_type": 4
            },
            {
                "track_no": 2,
                "music_id": 2037,
                "music_type": 4
            }
        ]
    },
    {
        "season_id": 12,
        "season_name": "SKILL ANALYZER 第4回 Bコース",
        "season_new_flg": true,
        "course_id": 12,
        "course_name": "SKILL ANALYZER Level.∞",
        "course_type": 3,
        "skill_level": 12,
        "skill_name_id": 12,
        "matching_assist": false,
        "clear_rate": 7125,
        "avg_score": 25834524,
        "tracks": [
            {
                "track_no": 0,
                "music_id": 2040,
                "music_type": 4
            },
            {
                "track_no": 1,
                "music_id": 2041,
                "music_type": 4
            },
            {
                "track_no": 2,
                "music_id": 2038,
                "music_type": 4
            }
        ]
    }
]